lytemaps/__init__.py
lytemaps/caret.py
lytemaps/civet.py
lytemaps/images.py
lytemaps/points.py
lytemaps/resampling.py
lytemaps/stats.py
lytemaps/transforms.py
lytemaps/utils.py
lytemaps/datasets/__init__.py
lytemaps/datasets/_osf.py
lytemaps/datasets/annotations.py
lytemaps/datasets/atlases.py
lytemaps/datasets/contributions.py
lytemaps/datasets/utils.py
lytemaps/datasets/data/osf.json
lytemaps/nulls/burt.py
lytemaps/nulls/spins.py
lytemaps-0.0.3.dist-info/LICENSE
lytemaps-0.0.3.dist-info/METADATA
lytemaps-0.0.3.dist-info/WHEEL
lytemaps-0.0.3.dist-info/top_level.txt
lytemaps-0.0.3.dist-info/RECORD
