Metadata-Version: 2.1
Name: lytemaps
Version: 0.0.3
Summary: Lightweight implementation of neuromaps
Author: Network Neuroscience Lab
Maintainer-email: Rastko Ciric <rastko@stanford.edu>
License: Attribution-NonCommercial-ShareAlike 4.0 International
Project-URL: Homepage, https://github.com/hypercoil/lytemaps
Classifier: Development Status :: 3 - Alpha
Classifier: Intended Audience :: Science/Research
Classifier: Programming Language :: Python :: 3
Classifier: License :: OSI Approved :: BSD License
Classifier: License :: Other/Proprietary License
Classifier: Operating System :: POSIX :: Linux
Classifier: Operating System :: MacOS :: MacOS X
Requires-Python: >=3.8
License-File: LICENSE
Requires-Dist: joblib
Requires-Dist: nibabel >=3.0.0
Requires-Dist: numpy >=1.14.0
Requires-Dist: pooch
Requires-Dist: scipy >=0.17
